zodbverify/__init__.py
zodbverify/__main__.py
zodbverify/entrypoint.py
zodbverify/verify.py
zodbverify/verify_oid.py
zodbverify-1.2.1.dist-info/licenses/LICENSE.GPL
zodbverify-1.2.1.dist-info/licenses/LICENSE.txt
zodbverify-1.2.1.dist-info/METADATA
zodbverify-1.2.1.dist-info/WHEEL
zodbverify-1.2.1.dist-info/entry_points.txt
zodbverify-1.2.1.dist-info/top_level.txt
zodbverify-1.2.1.dist-info/RECORD
