Metadata-Version: 2.4
Name: zodbverify
Version: 1.2.1
Summary: Check if all data from a ZODB can be loaded
Home-page: https://github.com/plone/zodbverify
Author: Plone Foundation Contributors
Author-email: releasemanager@plone.org
License: GNU General Public License v2 (GPLv2)
Keywords: ZODB,check,verification
Classifier: Development Status :: 4 - Beta
Classifier: Environment :: Web Environment
Classifier: Framework :: Zope
Classifier: Framework :: Zope :: 4
Classifier: Framework :: Zope :: 5
Classifier: Programming Language :: Python
Classifier: Programming Language :: Python :: 2.7
Classifier: Programming Language :: Python :: 3.6
Classifier: Programming Language :: Python :: 3.7
Classifier: Programming Language :: Python :: 3.8
Classifier: Programming Language :: Python :: 3.9
Classifier: Operating System :: OS Independent
Classifier: License :: OSI Approved :: GNU General Public License v2 (GPLv2)
License-File: LICENSE.GPL
License-File: LICENSE.txt
Requires-Dist: ZODB
Dynamic: license-file
